qase/__init__.py
qase/api_client_v1/__init__.py
qase/api_client_v1/api_client.py
qase/api_client_v1/api_response.py
qase/api_client_v1/configuration.py
qase/api_client_v1/exceptions.py
qase/api_client_v1/py.typed
qase/api_client_v1/rest.py
qase/api_client_v1/api/__init__.py
qase/api_client_v1/api/attachments_api.py
qase/api_client_v1/api/authors_api.py
qase/api_client_v1/api/cases_api.py
qase/api_client_v1/api/configurations_api.py
qase/api_client_v1/api/custom_fields_api.py
qase/api_client_v1/api/defects_api.py
qase/api_client_v1/api/environments_api.py
qase/api_client_v1/api/milestones_api.py
qase/api_client_v1/api/plans_api.py
qase/api_client_v1/api/projects_api.py
qase/api_client_v1/api/results_api.py
qase/api_client_v1/api/runs_api.py
qase/api_client_v1/api/search_api.py
qase/api_client_v1/api/shared_parameters_api.py
qase/api_client_v1/api/shared_steps_api.py
qase/api_client_v1/api/suites_api.py
qase/api_client_v1/api/system_fields_api.py
qase/api_client_v1/api/users_api.py
qase/api_client_v1/models/__init__.py
qase/api_client_v1/models/attachment.py
qase/api_client_v1/models/attachment_get.py
qase/api_client_v1/models/attachment_hash.py
qase/api_client_v1/models/attachment_list_response.py
qase/api_client_v1/models/attachment_list_response_all_of_result.py
qase/api_client_v1/models/attachment_response.py
qase/api_client_v1/models/attachment_uploads_response.py
qase/api_client_v1/models/attachmentupload.py
qase/api_client_v1/models/author.py
qase/api_client_v1/models/author_list_response.py
qase/api_client_v1/models/author_list_response_all_of_result.py
qase/api_client_v1/models/author_response.py
qase/api_client_v1/models/base_response.py
qase/api_client_v1/models/bulk200_response.py
qase/api_client_v1/models/bulk200_response_all_of_result.py
qase/api_client_v1/models/configuration_create.py
qase/api_client_v1/models/configuration_group.py
qase/api_client_v1/models/configuration_group_create.py
qase/api_client_v1/models/configuration_list_response.py
qase_api_client-2.0.3.dist-info/METADATA
qase_api_client-2.0.3.dist-info/WHEEL
qase_api_client-2.0.3.dist-info/top_level.txt
qase_api_client-2.0.3.dist-info/RECORD
